req_compile/__init__.py
req_compile/__main__.py
req_compile/candidates.py
req_compile/cmdline.py
req_compile/compile.py
req_compile/config.py
req_compile/containers.py
req_compile/dists.py
req_compile/errors.py
req_compile/filename.py
req_compile/utils.py
req_compile/versions.py
req_compile/metadata/__init__.py
req_compile/metadata/dist_info.py
req_compile/metadata/extractor.py
req_compile/metadata/metadata.py
req_compile/metadata/patch.py
req_compile/metadata/pyproject.py
req_compile/metadata/source.py
req_compile/repos/__init__.py
req_compile/repos/findlinks.py
req_compile/repos/multi.py
req_compile/repos/pypi.py
req_compile/repos/repository.py
req_compile/repos/solution.py
req_compile/repos/source.py
req_compile-0.10.21.dist-info/LICENSE.txt
req_compile-0.10.21.dist-info/METADATA
req_compile-0.10.21.dist-info/WHEEL
req_compile-0.10.21.dist-info/entry_points.txt
req_compile-0.10.21.dist-info/top_level.txt
req_compile-0.10.21.dist-info/RECORD
