Metadata-Version: 2.1
Name: req-compile
Version: 0.10.21
Summary: Python requirements compiler
Home-page: https://github.com/sputt/req-compile
Author: Spencer Putt
Author-email: sputt@alumni.iu.edu
License: MIT License
Platform: UNKNOWN
Classifier: Programming Language :: Python
Classifier: Programming Language :: Python :: 3.5
Classifier: Programming Language :: Python :: 3.6
Classifier: Programming Language :: Python :: 3.7
Classifier: Programming Language :: Python :: 3.8
Classifier: Operating System :: OS Independent
Classifier: Environment :: Console
Classifier: Topic :: Software Development
Classifier: Intended Audience :: Developers
Classifier: License :: OSI Approved :: MIT License
Requires-Python: >=2.7, !=3.0.*, !=3.1.*, !=3.2.*, !=3.3.*, !=3.4.*
License-File: LICENSE.txt
Requires-Dist: requests
Requires-Dist: six
Requires-Dist: toml
Requires-Dist: appdirs
Requires-Dist: packaging
Requires-Dist: wheel
Requires-Dist: functools32 ; python_version < "3.0"
Requires-Dist: enum34 ; python_version < "3.0"
Requires-Dist: typing ; python_version < "3.0"
